{
  "cashmere": {
    "positive_cues": [
      "목도리",
      "니트",
      "체온 섞인",
      "포근하게 감싸",
      "부드럽게 감싸",
      "몸에 닿은 따뜻한 천",
      "겨울 옷",
      "따뜻한 섬유",
      "오래 감고 있다가",
      "체온이 밴"
    ],
    "boost": 0.35
  },
  "warm_cotton": {
    "positive_cues": [
      "햇빛에 말린",
      "마른 티셔츠",
      "깨끗한 면",
      "체온이 남은 옷",
      "부드러운 천",
      "새로 빤",
      "보송",
      "체온 섞인"
    ],
    "boost": 0.28
  },
  "wool_blanket": {
    "positive_cues": [
      "목도리",
      "부드럽게 덮",
      "따뜻하게 덮",
      "겨울 옷",
      "까슬",
      "두꺼운 천",
      "포근하게 감싸"
    ],
    "boost": 0.3
  },
  "fresh_linen": {
    "positive_cues": [
      "햇빛에 말린 천",
      "세탁한 천",
      "새로 빤",
      "바짝 마른",
      "깨끗하고 보송",
      "얇은 천",
      "아침 햇빛",
      "갓 세탁한 리넨",
      "햇빛에 마른 천",
      "깨끗한 침구",
      "바짝 마른 섬유",
      "환한 청결감",
      "보송한 세탁물",
      "먼지 없는 천",
      "아침의 마른 침구",
      "하얗게 마른 천"
    ],
    "boost": 0.32,
    "negative_cues": [
      "가죽",
      "오크통",
      "담뱃잎",
      "젖은 도로",
      "숲 바닥"
    ]
  },
  "organza": {
    "positive_cues": [
      "얇고 투명한 천",
      "공기처럼 가벼운 천",
      "얇은 커튼",
      "커튼 사이로",
      "투명하고 가볍",
      "가볍게 떠",
      "공기가 지나가듯"
    ],
    "boost": 0.36
  },
  "silk": {
    "positive_cues": [
      "매끈한 천",
      "얇게 흐르는",
      "부드러운 광택",
      "차분한 광택",
      "매끄럽게 흐"
    ],
    "boost": 0.28
  },
  "velvet": {
    "positive_cues": [
      "두껍고 어두운 부드러움",
      "어두운 커튼",
      "두꺼운 커튼",
      "부드럽고 묵직",
      "묵직하게 내려앉",
      "어둡고 부드러운"
    ],
    "boost": 0.38
  },
  "butter_toast": {
    "positive_cues": [
      "버터",
      "빵",
      "토스트",
      "버터 바른 빵",
      "따뜻한 빵",
      "노릇한",
      "노릇하고 둥글",
      "녹은 지방감",
      "고소한 냄새"
    ],
    "boost": 0.36
  },
  "vanilla_cream": {
    "positive_cues": [
      "크림",
      "하얀 크림",
      "둥글고 매끈",
      "달콤한 느낌",
      "혀 위에서",
      "부드러운 단맛"
    ],
    "boost": 0.34
  },
  "roasted_almond": {
    "positive_cues": [
      "고소한",
      "오븐",
      "구운",
      "견과",
      "견과가루",
      "따뜻하고 살짝 메말라",
      "노릇한"
    ],
    "boost": 0.34
  },
  "burnt_sugar": {
    "positive_cues": [
      "카라멜",
      "달큰한",
      "설탕 가장자리",
      "검게 녹",
      "달고 어둡",
      "끈적",
      "입안에 남는 단맛"
    ],
    "boost": 0.34
  },
  "honeycomb": {
    "positive_cues": [
      "꿀",
      "촘촘한 틈",
      "천천히 배어",
      "끈적하고 빛나",
      "달큰한",
      "점성 있는 단맛"
    ],
    "boost": 0.36
  },
  "dark_chocolate": {
    "positive_cues": [
      "초콜릿",
      "어둡고 달",
      "쌉쌀한 단맛",
      "두껍고 어두운",
      "묵직한 단맛"
    ],
    "boost": 0.32
  },
  "film_grain": {
    "positive_cues": [
      "필름",
      "오래된 영화",
      "영화관",
      "빛 번짐",
      "노이즈",
      "흐릿하지만 감정",
      "낮은 해상도가 아니라 감성적인",
      "장면처럼",
      "노스텔지어",
      "기억처럼 남는",
      "입자가 부드럽게 남아"
    ],
    "boost": 0.42
  },
  "old_library": {
    "positive_cues": [
      "먼지 앉은 종이",
      "오래된 선반",
      "건조하고 조용한",
      "기억처럼 남는",
      "낡은 종이"
    ],
    "boost": 0.3
  },
  "late_night_air": {
    "positive_cues": [
      "어두운 공기",
      "조용하고 차분",
      "새벽이 지나기 전",
      "방 안의 어두운",
      "늦게 남는 공기",
      "늦은 밤 공기",
      "밤 창문",
      "조용한 밤공기",
      "새벽 전 공기",
      "감정이 가라앉은",
      "차갑고 조용한 공기",
      "밤의 서늘함",
      "낮의 열이 빠진",
      "창문을 열었을 때 들어오는 공기"
    ],
    "boost": 0.34,
    "negative_cues": [
      "여름 정오",
      "고해상도",
      "바닷바람",
      "따뜻한 빵",
      "크림"
    ]
  },
  "four_k_clarity": {
    "positive_cues": [
      "4k",
      "고해상도",
      "해상도",
      "초점",
      "윤곽",
      "또렷",
      "선명",
      "입자가 다 보",
      "디테일이 살아",
      "화면처럼",
      "깨끗하게 보이는",
      "정확히 맞은 화면"
    ],
    "boost": 0.42
  },
  "cut_diamond": {
    "positive_cues": [
      "차갑게 깎인",
      "유리 조각",
      "윤곽이 깨끗",
      "빛이 날카롭게",
      "건조하게 잘리는",
      "딱딱하게 끊기는"
    ],
    "boost": 0.32
  },
  "crystal": {
    "positive_cues": [
      "맑고 투명",
      "투명하게 위로",
      "깨끗하게 보이는",
      "차고 투명",
      "빛이 맑"
    ],
    "boost": 0.3
  },
  "slate": {
    "positive_cues": [
      "검은 판",
      "얇은 돌",
      "건조하게 잘리는",
      "딱딱하게 끊기는",
      "얇고 검은 판",
      "차갑고 건조하게",
      "점판암",
      "납작한 돌",
      "어두운 돌판",
      "차가운 얇은 돌",
      "매트한 검은 돌",
      "평평한 석판",
      "건조한 돌 표면",
      "층이 있는 돌",
      "차분한 미네랄",
      "얇게 잘린 돌"
    ],
    "boost": 0.38,
    "negative_cues": [
      "화강암 입자",
      "젖은 돌",
      "바닷바람",
      "따뜻한 빵",
      "크림"
    ]
  },
  "granite": {
    "positive_cues": [
      "화강암",
      "회색 암석",
      "차갑고 단단한",
      "거친 돌",
      "단단한 돌"
    ],
    "boost": 0.28
  },
  "wet_stone": {
    "positive_cues": [
      "젖은 돌",
      "차가운 돌",
      "비 맞은 바위",
      "석재",
      "물기 냄새",
      "물기 어린 돌",
      "차가운 젖은 표면",
      "계곡 옆 자갈",
      "젖은 미네랄",
      "축축한 광물감",
      "물 지난 돌",
      "젖은 회색 돌",
      "바위에 남은 물기"
    ],
    "boost": 0.36,
    "negative_cues": [
      "따뜻한 빵",
      "크림",
      "바닷바람",
      "가죽",
      "마른 허브"
    ]
  },
  "wet_moss": {
    "positive_cues": [
      "계곡 이끼",
      "축축한 초록",
      "초록색 냄새",
      "숲길 바닥",
      "비가 그친 숲",
      "차갑고 축축한 초록",
      "초록의 숨"
    ],
    "boost": 0.38
  },
  "cold_metal": {
    "positive_cues": [
      "금속성",
      "메탈릭",
      "차갑고 단단한",
      "찬 수저",
      "깨끗한 메탈릭",
      "오래 남는 금속"
    ],
    "boost": 0.36
  },
  "silver_spoon": {
    "positive_cues": [
      "입안에 찬 수저",
      "찬 수저",
      "수저를 문",
      "깨끗한 메탈릭",
      "입안에",
      "오래 남아",
      "은수저",
      "은색 숟가락",
      "금속 맛",
      "차가운 숟가락",
      "입안의 금속성",
      "은빛 금속",
      "깨끗한 금속 맛",
      "혀에 닿는 차가운 금속",
      "작은 금속성",
      "차갑게 남는 금속"
    ],
    "boost": 0.38,
    "negative_cues": [
      "가죽",
      "나무껍질",
      "바닷바람",
      "크림",
      "젖은 흙"
    ]
  },
  "mountain_stream": {
    "positive_cues": [
      "산길 옆 맑은 물",
      "맑은 물소리",
      "차고 투명하게",
      "위로 흐르는",
      "맑게 흐르는",
      "물소리처럼"
    ],
    "boost": 0.38
  },
  "cold_fog": {
    "positive_cues": [
      "낮게 깔린",
      "흰 숨",
      "서늘하고 흐릿",
      "흐릿하게 퍼지는",
      "차가운 숨"
    ],
    "boost": 0.34
  },
  "citrus_peel": {
    "positive_cues": [
      "껍질을 비틀",
      "오일이 톡",
      "톡 튀",
      "맑은 오일",
      "차갑게 올라와"
    ],
    "boost": 0.36
  },
  "black_tea": {
    "positive_cues": [
      "진하게 우린",
      "잎물",
      "말린 잎",
      "쌉쌀함",
      "조용히 남아",
      "우린 잎",
      "홍차",
      "마른 찻잎",
      "찻잔 위로 오르는 향",
      "살짝 떫은",
      "우디한 차 향",
      "오후의 티룸",
      "건조한 잎차",
      "차분하고 떫은 식물감",
      "따뜻한 찻잎",
      "낡은 종이와 차"
    ],
    "boost": 0.34,
    "negative_cues": [
      "크림",
      "바닷바람",
      "젖은 도로",
      "고해상도",
      "은수저"
    ]
  },
  "fireplace_ash": {
    "positive_cues": [
      "식은 재",
      "손끝에 묻",
      "회색빛으로 부서",
      "건조하고 회색",
      "재가"
    ],
    "boost": 0.36
  },
  "bark": {
    "positive_cues": [
      "나무껍질",
      "거친 나무 표면",
      "흙 묻은 나무",
      "갈라진 줄기",
      "마른 껍질",
      "울퉁불퉁한 목질감",
      "숲속 오래된 줄기",
      "거칠고 드라이한 나무",
      "초록 잎보다 갈색 껍질",
      "손에 걸리는 나무 표면"
    ],
    "negative_cues": [
      "바닷바람",
      "해안가",
      "깨끗한 방",
      "크림",
      "고해상도"
    ],
    "boost": 0.36
  },
  "sea_breeze": {
    "positive_cues": [
      "바닷바람",
      "소금기 어린 공기",
      "해안가의 차가운 바람",
      "넓게 퍼지는 짠 공기",
      "젖은 해변의 공기",
      "바다에서 밀려오는 서늘함",
      "해풍처럼 맑고 짠 느낌",
      "물기와 소금기가 같이 느껴지는 향",
      "수평으로 열리는 공기",
      "짠 바람"
    ],
    "negative_cues": [
      "숲",
      "계곡",
      "바위틈",
      "흙냄새",
      "오크통",
      "가죽"
    ],
    "boost": 0.38
  },
  "rain_on_asphalt": {
    "positive_cues": [
      "비 맞은 아스팔트",
      "젖은 도로 냄새",
      "여름비가 내린 도로",
      "빗물에 달아오른 포장도로",
      "도시의 젖은 바닥",
      "비 온 뒤 차가운 아스팔트",
      "먼지와 빗물이 섞인 냄새",
      "젖은 콘크리트보다 더 도시적인 느낌",
      "포장도로에서 올라오는 비 냄새",
      "도로가 식으면서 나는 냄새"
    ],
    "negative_cues": [
      "정원",
      "잎사귀",
      "숲 바닥",
      "바닷바람",
      "크림"
    ],
    "boost": 0.38
  },
  "rainy_street": {
    "positive_cues": [
      "비 오는 거리",
      "젖은 도시 공기",
      "가로등 아래 빗물",
      "우산 아래 도로",
      "젖은 보도블록",
      "비 내린 골목",
      "도시의 빗내",
      "도로 위 반사광",
      "축축한 거리",
      "차가운 거리의 습기"
    ],
    "negative_cues": [
      "숲",
      "정원",
      "바다",
      "따뜻한 빵",
      "오래된 도서관"
    ],
    "boost": 0.36
  },
  "leather": {
    "positive_cues": [
      "오래된 가죽 소파",
      "마른 가죽 재킷",
      "동물성이고 드라이한 향",
      "어둡고 매트한 가죽 질감",
      "새 가죽보다 오래된 가죽",
      "가죽 가방 안쪽 냄새",
      "묵직하고 건조한 동물성 느낌",
      "스모키하지는 않지만 어두운 질감",
      "낡은 가죽",
      "가죽 안감"
    ],
    "negative_cues": [
      "갓 세탁한",
      "바닷바람",
      "크리스탈",
      "고해상도",
      "초록 줄기"
    ],
    "boost": 0.38
  },
  "suede": {
    "positive_cues": [
      "스웨이드처럼 보송한 질감",
      "부드럽지만 매트한 가죽",
      "짧은 털감이 있는 가죽",
      "가루처럼 부드러운 표면",
      "포근하지만 드라이한 촉감",
      "매끈한 가죽보다 더 보송한 느낌",
      "벨벳보다 건조하고 가죽에 가까운 질감",
      "따뜻하고 낮게 깔리는 부드러움",
      "보송한 가죽",
      "매트한 털감"
    ],
    "negative_cues": [
      "젖은 도로",
      "바닷바람",
      "금속 맛",
      "크리스탈",
      "초록 줄기"
    ],
    "boost": 0.38
  },
  "tobacco_leaf": {
    "positive_cues": [
      "담뱃잎",
      "마른 담뱃잎",
      "어둡고 달큰한 잎",
      "숙성된 잎",
      "갈색 잎 냄새",
      "가죽과 잎이 섞인",
      "오래 묵은 식물성",
      "건조하고 어두운 잎",
      "말린 잎의 단맛",
      "담배잎 같은"
    ],
    "negative_cues": [
      "갓 세탁한",
      "바닷바람",
      "시트러스",
      "크리스탈",
      "깨끗한 방"
    ],
    "boost": 0.36
  },
  "cedarwood": {
    "positive_cues": [
      "시더우드",
      "깨끗한 나무향",
      "마른 목재",
      "연필 깎은 나무",
      "정돈된 우디함",
      "건조한 나무결",
      "곧게 뻗는 목재감",
      "습기 없는 나무",
      "차분한 나무 표면",
      "드라이한 우디"
    ],
    "negative_cues": [
      "바닷바람",
      "크림",
      "젖은 도로",
      "담뱃잎",
      "탄 나무"
    ],
    "boost": 0.34
  },
  "green_stem": {
    "positive_cues": [
      "초록 줄기",
      "줄기를 꺾은 냄새",
      "풋내",
      "물기 있는 줄기",
      "푸른 줄기 단면",
      "싱그러운 줄기",
      "아삭한 녹색감",
      "꺾인 풀대",
      "푸른 물기",
      "어린 줄기 향"
    ],
    "negative_cues": [
      "마른 허브",
      "담뱃잎",
      "오래된 가죽",
      "오크통",
      "탄 나무"
    ],
    "boost": 0.36
  },
  "dry_herb": {
    "positive_cues": [
      "마른 허브",
      "말린 풀",
      "바스러지는 잎",
      "건조한 잎가루",
      "씁쓸한 허브",
      "가벼운 식물 가루",
      "주방 선반의 허브",
      "햇빛에 마른 풀",
      "드라이한 식물감",
      "손가락 사이 부서지는 잎"
    ],
    "negative_cues": [
      "초록 줄기",
      "젖은 이끼",
      "크림",
      "바닷바람",
      "젖은 도로"
    ],
    "boost": 0.34
  },
  "clean_room": {
    "positive_cues": [
      "깨끗한 방",
      "먼지 없이 정돈된",
      "환기된 방",
      "세탁한 공기",
      "밝고 건조한 공간",
      "정리된 아침 공기",
      "하얀 청결감",
      "방금 환기한 느낌",
      "물기 없는 깨끗함",
      "정돈된 실내 공기"
    ],
    "negative_cues": [
      "오크통",
      "담뱃잎",
      "숲 바닥",
      "비 맞은 아스팔트",
      "가죽"
    ],
    "boost": 0.34
  },
  "barrel_cellar": {
    "positive_cues": [
      "오크통 숙성고",
      "어두운 저장고",
      "습한 나무 저장고",
      "술기운이 밴 나무",
      "숙성된 지하실",
      "차가운 오크통",
      "두꺼운 숙성감",
      "지하 셀러",
      "나무와 습도가 섞인 공간",
      "오래 묵은 저장고"
    ],
    "negative_cues": [
      "깨끗한 방",
      "바닷바람",
      "갓 세탁한",
      "4k",
      "시트러스"
    ],
    "boost": 0.38
  },
  "charred_oak": {
    "positive_cues": [
      "그을린 오크",
      "탄 오크",
      "탄 나무의 단맛",
      "스모키한 목재",
      "오크통 안쪽의 그을림",
      "드라이한 탄 목재",
      "나무결이 살아 있는 탄 향",
      "그을린 나무 표면",
      "달큰하게 탄 나무",
      "숙성된 탄 오크"
    ],
    "negative_cues": [
      "깨끗한 방",
      "바닷바람",
      "초록 줄기",
      "크림",
      "은수저"
    ],
    "boost": 0.38
  },
  "forest_floor": {
    "positive_cues": [
      "숲 바닥",
      "젖은 낙엽",
      "흙과 낙엽",
      "비 온 뒤 숲",
      "낮게 깔린 숲 냄새",
      "어두운 식물감",
      "나무껍질과 흙",
      "그늘진 숲의 습도",
      "축축한 숲 바닥",
      "갈색 초록 습기"
    ],
    "negative_cues": [
      "바닷바람",
      "깨끗한 방",
      "고해상도",
      "은수저",
      "크림"
    ],
    "boost": 0.38
  }
}
